[{"title": "财富宝投融", "platEarnings": 0, "term": -1, "onlineDate": "2014-04-17", "cityName": "四川|成都", "url": "http://www.wdzj.com/dangan/cfbtr/", "registeredCapital": 1000}, {"title": "宏图创投", "platEarnings": 0, "term": -1, "onlineDate": "2015-03-12", "cityName": "山东|潍坊", "url": "http://www.wdzj.com/dangan/htct/", "registeredCapital": 1000}, {"title": "顺融易贷", "platEarnings": 0, "term": -1, "onlineDate": "2015-03-16", "cityName": "山东|莱芜", "url": "http://www.wdzj.com/dangan/sryd/", "registeredCapital": 100}, {"title": "华源投资", "platEarnings": 0, "term": -1, "onlineDate": "2015-08-10", "cityName": "北京|顺义", "url": "http://www.wdzj.com/dangan/hytz2/", "registeredCapital": 10000}, {"title": "雍铄金融", "platEarnings": 0, "term": -1, "onlineDate": "2017-03-29", "cityName": "北京|丰台", "url": "http://www.wdzj.com/dangan/ysjr4/", "registeredCapital": 10000}, {"title": "中诚财富", "platEarnings": 0, "term": -1, "onlineDate": "2015-01-29", "cityName": "河南|郑州", "url": "http://www.wdzj.com/dangan/zccf/", "registeredCapital": 10000}, {"title": "宜信惠民", "platEarnings": 0, "term": -1, "onlineDate": "2016-07-19", "cityName": "北京|朝阳", "url": "http://www.wdzj.com/dangan/yx/", "registeredCapital": 10000}, {"title": "乐融巴巴", "platEarnings": 15, "term": -1, "onlineDate": "2011-03-28", "cityName": "新疆|乌鲁木齐", "url": "http://www.wdzj.com/dangan/lrbb/", "registeredCapital": 1000}, {"title": "易融投资", "platEarnings": 0, "term": -1, "onlineDate": "2015-08-27", "cityName": "广东|深圳", "url": "http://www.wdzj.com/dangan/yrtz/", "registeredCapital": 1000}, {"title": "中融网金所", "platEarnings": 0, "term": -1, "onlineDate": "2014-10-15", "cityName": "北京|石景山", "url": "http://www.wdzj.com/dangan/zrwjs/", "registeredCapital": 5000}, {"title": "幸福e贷", "platEarnings": 0, "term": -1, "onlineDate": "2013-08-20", "cityName": "广东|深圳", "url": "http://www.wdzj.com/dangan/xfed/", "registeredCapital": -1}, {"title": "信财贷", "platEarnings": 25, "term": -1, "onlineDate": "2014-07-09", "cityName": "浙江|杭州", "url": "http://www.wdzj.com/dangan/xcd/", "registeredCapital": 3000}, {"title": "润恒贷", "platEarnings": 19, "term": -1, "onlineDate": "2014-10-11", "cityName": "河南|郑州", "url": "http://www.wdzj.com/dangan/rhd1/", "registeredCapital": 5100}, {"title": "鹏天投资", "platEarnings": 0, "term": -1, "onlineDate": "2014-12-24", "cityName": "四川|成都", "url": "http://www.wdzj.com/dangan/pttz/", "registeredCapital": 1000}, {"title": "乐天在线", "platEarnings": 0, "term": -1, "onlineDate": "2014-09-12", "cityName": "山东|德州", "url": "http://www.wdzj.com/dangan/ltzx/", "registeredCapital": 1000}, {"title": "中银信投资", "platEarnings": 0, "term": -1, "onlineDate": "2015-07-01", "cityName": "湖北|武汉", "url": "http://www.wdzj.com/dangan/zyxtz/", "registeredCapital": 3000}, {"title": "仟佰贷", "platEarnings": 0, "term": -1, "onlineDate": "2014-09-01", "cityName": "河南|郑州", "url": "http://www.wdzj.com/dangan/qbd2/", "registeredCapital": 1000}, {"title": "聚汇投资", "platEarnings": 0, "term": -1, "onlineDate": "2014-12-22", "cityName": "山东|潍坊", "url": "http://www.wdzj.com/dangan/jhtz/", "registeredCapital": 500}, {"title": "万博基业", "platEarnings": 0, "term": -1, "onlineDate": "2015-01-09", "cityName": "北京|通州", "url": "http://www.wdzj.com/dangan/wbjy/", "registeredCapital": 5000}, {"title": "富源财富", "platEarnings": 0, "term": -1, "onlineDate": "2015-03-20", "cityName": "山东|泰安", "url": "http://www.wdzj.com/dangan/fycf2/", "registeredCapital": 1000}, {"title": "中汇通投资", "platEarnings": 0, "term": -1, "onlineDate": "2015-08-26", "cityName": "广西|南宁", "url": "http://www.wdzj.com/dangan/zhttz/", "registeredCapital": 10000}, {"title": "钱途贷", "platEarnings": 15, "term": -1, "onlineDate": "2014-03-25", "cityName": "北京|丰台", "url": "http://www.wdzj.com/dangan/qtd/", "registeredCapital": 1000}, {"title": "首信贷", "platEarnings": 0, "term": -1, "onlineDate": "2015-01-12", "cityName": "北京|西城", "url": "http://www.wdzj.com/dangan/sxd5/", "registeredCapital": 10000}, {"title": "水晶贷", "platEarnings": 0, "term": -1, "onlineDate": "2015-06-01", "cityName": "江苏|连云港", "url": "http://www.wdzj.com/dangan/sjd3/", "registeredCapital": 2000}, {"title": "信任时贷", "platEarnings": 14, "term": -1, "onlineDate": "2014-07-10", "cityName": "上海|浦东", "url": "http://www.wdzj.com/dangan/xrsd/", "registeredCapital": 2000}]