[{"title": "德丰投资", "platEarnings": 0, "term": -1, "onlineDate": "2014-02-01", "cityName": "四川|宜宾", "url": "http://www.wdzj.com/dangan/dfcf/", "registeredCapital": 1000}, {"title": "楚商创投", "platEarnings": 0, "term": -1, "onlineDate": "2014-01-01", "cityName": "云南|昆明", "url": "http://www.wdzj.com/dangan/csct/", "registeredCapital": 3000}, {"title": "网赢天下", "platEarnings": 0, "term": -1, "onlineDate": "2013-03-01", "cityName": "广东|深圳", "url": "http://www.wdzj.com/dangan/wytx/", "registeredCapital": 2000}, {"title": "讯燕金服", "platEarnings": 0, "term": -1, "onlineDate": "2015-03-12", "cityName": "江苏|苏州", "url": "http://www.wdzj.com/dangan/xyjf/", "registeredCapital": 1000}, {"title": "鼎方投资", "platEarnings": 0, "term": -1, "onlineDate": "2015-12-07", "cityName": "河北|石家庄", "url": "http://www.wdzj.com/dangan/dftz1/", "registeredCapital": 3000}, {"title": "凤城贷", "platEarnings": 0, "term": -1, "onlineDate": "2015-01-28", "cityName": "山东|滨州", "url": "http://www.wdzj.com/dangan/fcd1/", "registeredCapital": 1100}, {"title": "温商金融", "platEarnings": 0, "term": -1, "onlineDate": "2014-12-19", "cityName": "浙江|温州", "url": "http://www.wdzj.com/dangan/wsjr/", "registeredCapital": 1288}, {"title": "活宝汇", "platEarnings": 0, "term": -1, "onlineDate": "2014-12-01", "cityName": "广东|深圳", "url": "http://www.wdzj.com/dangan/hbh/", "registeredCapital": 10000}, {"title": "甬发贷", "platEarnings": 0, "term": -1, "onlineDate": "2014-08-26", "cityName": "浙江|宁波", "url": "http://www.wdzj.com/dangan/yfd3/", "registeredCapital": 500}, {"title": "汇凯鑫创投", "platEarnings": 0, "term": -1, "onlineDate": "2014-09-01", "cityName": "广东|深圳", "url": "http://www.wdzj.com/dangan/hkxct/", "registeredCapital": 100000}, {"title": "春强财富", "platEarnings": 0, "term": -1, "onlineDate": "2014-12-08", "cityName": "山东|滨州", "url": "http://www.wdzj.com/dangan/cqcf/", "registeredCapital": 1000}, {"title": "汾湖投资", "platEarnings": 0, "term": -1, "onlineDate": "2015-01-01", "cityName": "广东|深圳", "url": "http://www.wdzj.com/dangan/fhtz/", "registeredCapital": 10000}, {"title": "鲁润创投", "platEarnings": 0, "term": -1, "onlineDate": "2014-11-27", "cityName": "河北|衡水", "url": "http://www.wdzj.com/dangan/lrct/", "registeredCapital": 1000}, {"title": "鼎和资本", "platEarnings": 0, "term": -1, "onlineDate": "2015-03-25", "cityName": "江苏|苏州", "url": "http://www.wdzj.com/dangan/dhzb/", "registeredCapital": 12000}, {"title": "米迪熊", "platEarnings": 0, "term": -1, "onlineDate": "2016-04-29", "cityName": "广东|深圳", "url": "http://www.wdzj.com/dangan/mdx/", "registeredCapital": 11000}, {"title": "耀毅投资", "platEarnings": 0, "term": -1, "onlineDate": "2015-09-29", "cityName": "山东|临沂", "url": "http://www.wdzj.com/dangan/yytz3/", "registeredCapital": 3000}, {"title": "商鼎贷", "platEarnings": 0, "term": -1, "onlineDate": "2015-04-02", "cityName": "上海|金山", "url": "http://www.wdzj.com/dangan/sdd3/", "registeredCapital": 5001}, {"title": "晨升投资", "platEarnings": 0, "term": -1, "onlineDate": "2015-04-27", "cityName": "云南|昆明", "url": "http://www.wdzj.com/dangan/cstz/", "registeredCapital": 1000}, {"title": "学贷网", "platEarnings": 0, "term": -1, "onlineDate": "2014-04-09", "cityName": "四川|成都", "url": "http://www.wdzj.com/dangan/xdw/", "registeredCapital": 10080}, {"title": "e云贷", "platEarnings": 0, "term": -1, "onlineDate": "2013-08-01", "cityName": "北京|朝阳", "url": "http://www.wdzj.com/dangan/eyd/", "registeredCapital": 100}, {"title": "平福投资", "platEarnings": 0, "term": -1, "onlineDate": "2015-01-04", "cityName": "江苏|淮安", "url": "http://www.wdzj.com/dangan/pftz/", "registeredCapital": 1000}, {"title": "邦众财富", "platEarnings": 0, "term": -1, "onlineDate": "2014-12-29", "cityName": "福建|福州", "url": "http://www.wdzj.com/dangan/bzcf2/", "registeredCapital": 5280}, {"title": "融通聚富", "platEarnings": 0, "term": -1, "onlineDate": "2014-03-18", "cityName": "广东|深圳", "url": "http://www.wdzj.com/dangan/rjcf/", "registeredCapital": 2000}, {"title": "短平快理财", "platEarnings": 0, "term": -1, "onlineDate": "2016-03-17", "cityName": "广东|深圳", "url": "http://www.wdzj.com/dangan/dpklc/", "registeredCapital": 10300}, {"title": "创赢贷", "platEarnings": 0, "term": -1, "onlineDate": "2015-09-21", "cityName": "广东|深圳", "url": "http://www.wdzj.com/dangan/cyd6/", "registeredCapital": 1000}]