{"pageSize": 25, "currentPage": 26, "maxElements": 5594, "totalPage": 224, "liststep": 2, "listbegin": 25, "listend": 27, "offset": 0, "list": [{"platStatus": 1, "firstPin": "F", "platEarnings": 0, "zonghezhishuRank": 0, "salaryguard": 4.5, "onlineDate": "2014-01-01", "cityName": "广东|深圳", "platNamePin": "ftd", "registeredCapital": 5000, "platIconUrl": "http://www.wdzj.com/wdzj/images/plat/icon/547.jpg", "gjlhhFlag": "0", "platName": "富通贷", "term": "3月标(45.0%)、24月以上标(22.0%)", "platId": 547, "serviceAttitude": 4.0, "withdrawSpeed": 3.0, "websiteExperience": 4.0, "tzjPj": "", "zonghezhishu": 0}, {"platStatus": 5, "firstPin": "Z", "platEarnings": 0, "zonghezhishuRank": 0, "onlineDate": "2015-04-29", "cityName": "山东|潍坊", "platNamePin": "zhct", "platIconUrl": "http://www.wdzj.com/wdzj/images/plat/icon/1896.jpg", "registeredCapital": 3000, "gjlhhFlag": "0", "platName": "正和创投", "term": "天标(100%)", "platId": 1896, "tzjPj": "", "zonghezhishu": 0}, {"platStatus": 1, "firstPin": "C", "platEarnings": 13.82, "zonghezhishuRank": 0, "salaryguard": 3.5794, "onlineDate": "2015-02-10", "androidUrl": "http://a.app.qq.com/o/simple.jsp?pkgname=com.jbr.kullo.chengtounet", "cityName": "湖北|武汉", "platNamePin": "ctzx1", "registeredCapital": 5000, "platIconUrl": "http://www.wdzj.com/wdzj/images/plat/icon/1616.jpg", "gjlhhFlag": "0", "platName": "诚投在线", "term": "6-12月标(63.2%)", "platId": 1616, "serviceAttitude": 3.3889, "withdrawSpeed": 2.8571, "websiteExperience": 3.3492, "wechat": "http://openplat.wdzj.com/upload/plats/1616/20160901104727s_.jpg", "iosUrl": "", "tzjPj": "", "zonghezhishu": 0}, {"platStatus": 2, "firstPin": "H", "platEarnings": 12, "zonghezhishuRank": 0, "salaryguard": 3.0, "onlineDate": "2015-01-16", "cityName": "辽宁|朝阳", "platNamePin": "htw", "registeredCapital": 2000, "platIconUrl": "http://www.wdzj.com/wdzj/images/plat/icon/1362.jpg", "gjlhhFlag": "0", "platName": "宏泰网", "term": "2月标(80%)、4-6月标(10%)", "platId": 1362, "serviceAttitude": 4.0, "withdrawSpeed": 2.6667, "websiteExperience": 4.3333, "tzjPj": "", "zonghezhishu": 0}, {"platStatus": 1, "firstPin": "C", "platEarnings": 0, "zonghezhishuRank": 0, "salaryguard": 3.25, "onlineDate": "2015-11-05", "androidUrl": "http://a.app.qq.com/o/simple.jsp?pkgname=com.cainew.cainewonline", "cityName": "浙江|宁波", "platNamePin": "cnqd", "registeredCapital": 10000, "platIconUrl": "http://openplat.wdzj.com/upload/plats/4332/20160427143115s_.png", "gjlhhFlag": "0", "platName": "菜牛钱袋", "term": "24月以上标(25.0%)、3月标(25.0%)", "platId": 4332, "serviceAttitude": 3.0, "withdrawSpeed": 2.25, "websiteExperience": 2.5, "wechat": "http://openplat.wdzj.com/upload/plats/4332/20160428143136s_.jpg", "iosUrl": "https://itunes.apple.com/cn/app/cai-niu-qian-dai-gao-shou/id1073515357?l=en&mt=8", "tzjPj": "", "zonghezhishu": 0}, {"platStatus": 3, "firstPin": "D", "platEarnings": 18, "zonghezhishuRank": 0, "onlineDate": "2015-05-28", "cityName": "上海|杨浦", "platNamePin": "djcf", "platIconUrl": "http://openplat.wdzj.com/upload/plats/2086/20150609163852s_.JPG", "registeredCapital": 8000, "gjlhhFlag": "0", "platName": "殿金财富", "term": "1月标(50%)、天标(50%)", "platId": 2086, "tzjPj": "", "zonghezhishu": 0}, {"platStatus": 3, "firstPin": "T", "platEarnings": 12, "zonghezhishuRank": 0, "salaryguard": 2.6667, "onlineDate": "2014-10-16", "cityName": "浙江|杭州", "platNamePin": "tcw2", "registeredCapital": 1000, "platIconUrl": "http://www.wdzj.com/wdzj/images/plat/icon/2062.jpg", "gjlhhFlag": "0", "platName": "涛财网", "term": "天标(64%)、1月标(31%)", "platId": 2062, "serviceAttitude": 3.0, "withdrawSpeed": 2.0, "websiteExperience": 3.0, "tzjPj": "", "zonghezhishu": 0}, {"platStatus": 1, "firstPin": "X", "platEarnings": 11.94, "zonghezhishuRank": 0, "salaryguard": 3.5714, "onlineDate": "2015-04-01", "androidUrl": "http://android.myapp.com/myapp/detail.htm?apkName=com.comdo.newup", "cityName": "浙江|杭州", "platNamePin": "xsd8", "registeredCapital": 5000, "platIconUrl": "http://openplat.wdzj.com/upload/plats/4389/20160616104938s_.jpg", "gjlhhFlag": "0", "platName": "新升贷", "term": "6-12月标(2.0%)", "platId": 4389, "serviceAttitude": 3.8571, "withdrawSpeed": 2.2857, "websiteExperience": 3.3571, "wechat": "http://openplat.wdzj.com/upload/plats/4389/20160809104616s_.jpg", "iosUrl": "https://itunes.apple.com/cn/app/xin-sheng-dai-for-iphone/id1137019883?mt=8", "tzjPj": "", "zonghezhishu": 0}, {"platStatus": 1, "firstPin": "X", "platEarnings": 0, "zonghezhishuRank": 0, "onlineDate": "2017-05-10", "salaryguard": 4.4545, "androidUrl": "http://a.app.qq.com/o/simple.jsp?pkgname=com.newenergyjinfu.jytz", "cityName": "浙江|杭州", "platNamePin": "xnyjf", "platIconUrl": "http://openplat.wdzj.com/upload/plats/6476/20170516091319s_.png", "registeredCapital": 6000, "gjlhhFlag": "0", "platName": "新能源金服", "platId": 6476, "withdrawSpeed": 3.0455, "serviceAttitude": 4.3409, "websiteExperience": 4.3409, "wechat": "http://openplat.wdzj.com/upload/plats/6476/20170516135457s_.png", "iosUrl": "https://itunes.apple.com/cn/app/id1223879897?mt=8", "tzjPj": "", "zonghezhishu": 0}, {"platStatus": 1, "firstPin": "T", "platEarnings": 0, "zonghezhishuRank": 0, "onlineDate": "2015-06-28", "salaryguard": 4.6515, "androidUrl": "http://android.myapp.com/myapp/detail.htm?apkName=com.touzila.tiancaibao", "cityName": "北京|东城", "platNamePin": "tcb", "platIconUrl": "http://openplat.wdzj.com/upload/plats/5387/20170615162331s_.png", "registeredCapital": 10000, "gjlhhFlag": "0", "platName": "天财宝", "term": "6-12月标(89.0%)、3月标(9.0%)", "platId": 5387, "withdrawSpeed": 4.7727, "serviceAttitude": 4.6818, "websiteExperience": 4.6667, "wechat": "http://openplat.wdzj.com/upload/plats/5387/20170801155109s_.png", "iosUrl": "https://itunes.apple.com/cn/app/id998781312?mt=8", "tzjPj": "", "zonghezhishu": 0}, {"platStatus": 3, "firstPin": "H", "platEarnings": 10.8, "zonghezhishuRank": 0, "salaryguard": 2.5814, "onlineDate": "2015-01-05", "androidUrl": "http://a.app.qq.com/o/simple.jsp?pkgname=com.haihefinance", "cityName": "天津|东丽", "platNamePin": "hhjr2", "registeredCapital": 5556, "platIconUrl": "http://openplat.wdzj.com/upload/plats/4276/20160819161522s_.png", "gjlhhFlag": "0", "platName": "海河金融", "term": "24月以上标(48.0%)、12-24月标(17.0%)", "platId": 4276, "serviceAttitude": 2.6628, "withdrawSpeed": 1.8605, "websiteExperience": 2.593, "wechat": "http://openplat.wdzj.com/upload/plats/4276/20160822150302s_.png", "iosUrl": "https://itunes.apple.com/WebObjects/MZStore.woa/wa/viewSoftware?id=1061002503", "tzjPj": "", "zonghezhishu": 0}, {"platStatus": 1, "firstPin": "Q", "platEarnings": 0, "zonghezhishuRank": 0, "salaryguard": 4.0, "onlineDate": "2017-04-14", "androidUrl": "http://openbox.mobilem.360.cn/index/d/sid/3769190", "cityName": "浙江|杭州", "platNamePin": "qllc", "registeredCapital": 5000, "platIconUrl": "http://openplat.wdzj.com/upload/plats/6375/20170420115820s_.png", "gjlhhFlag": "0", "platName": "钱路理财", "term": "1月标(70.0%)、3月标(20.0%)", "platId": 6375, "serviceAttitude": 5.0, "withdrawSpeed": 2.0, "websiteExperience": 5.0, "wechat": "http://openplat.wdzj.com/upload/plats/6375/20170329154901s_.jpg", "iosUrl": "https://itunes.apple.com/cn/app/id1219138359?mt=8", "tzjPj": "", "zonghezhishu": 0}, {"platStatus": 1, "firstPin": "X", "platEarnings": 11.94, "zonghezhishuRank": 0, "salaryguard": 4.2105, "onlineDate": "2015-04-25", "androidUrl": "", "cityName": "吉林|白城", "platNamePin": "xpd", "registeredCapital": 2000, "platIconUrl": "http://openplat.wdzj.com/upload/plats/3148/20170828091628s_.png", "gjlhhFlag": "0", "platName": "小平贷", "term": "6-12月标(21.6%)", "platId": 3148, "serviceAttitude": 4.6842, "withdrawSpeed": 3.7368, "websiteExperience": 4.0, "wechat": "http://openplat.wdzj.com/upload/plats/3148/20170322130748s_.jpg", "iosUrl": "", "tzjPj": "", "zonghezhishu": 0}, {"platStatus": 1, "firstPin": "C", "platEarnings": 0, "zonghezhishuRank": 0, "salaryguard": 5.0, "onlineDate": "2016-03-07", "androidUrl": "http://www.echangyun.com/app/download", "cityName": "湖南|株洲", "platNamePin": "cyw1", "registeredCapital": 1000, "platIconUrl": "http://openplat.wdzj.com/upload/plats/6559/20170706112441s_.jpg", "gjlhhFlag": "0", "platName": "长运网", "term": "1月标(38.0%)、3月标(30.0%)", "platId": 6559, "serviceAttitude": 4.8182, "withdrawSpeed": 4.1818, "websiteExperience": 4.3636, "wechat": "http://openplat.wdzj.com/upload/plats/6559/20170707115137s_.jpg", "iosUrl": "https://itunes.apple.com/cn/app/zhang-yun-wang/id1111473762?l=en&mt=8", "tzjPj": "", "zonghezhishu": 0}, {"platStatus": 3, "firstPin": "Z", "platEarnings": 0, "zonghezhishuRank": 0, "salaryguard": 1.5, "onlineDate": "2014-04-01", "cityName": "北京|朝阳", "platNamePin": "zxzx", "registeredCapital": 5006, "platIconUrl": "http://www.wdzj.com/wdzj/images/plat/icon/632.jpg", "gjlhhFlag": "0", "platName": "众信在线", "platId": 632, "serviceAttitude": 1.75, "withdrawSpeed": 1.25, "websiteExperience": 1.75, "tzjPj": "", "zonghezhishu": 0}, {"platStatus": 1, "firstPin": "O", "platEarnings": 12, "zonghezhishuRank": 0, "onlineDate": "2015-01-18", "cityName": "浙江|温州", "platNamePin": "ojs", "platIconUrl": "http://openplat.wdzj.com/upload/plats/1877/20150429164411s_.jpg", "registeredCapital": 1000, "gjlhhFlag": "0", "platName": "瓯金所", "term": "天标(90%)、4-6月标(10%)", "platId": 1877, "tzjPj": "", "zonghezhishu": 0}, {"platStatus": 5, "firstPin": "Y", "platEarnings": 25, "zonghezhishuRank": 0, "onlineDate": "2014-11-11", "salaryguard": 3.25, "cityName": "浙江|宁波", "platNamePin": "yxct", "platIconUrl": "http://www.wdzj.com/wdzj/images/plat/icon/1579.jpg", "registeredCapital": 5000, "gjlhhFlag": "0", "platName": "融信贷", "platId": 1579, "withdrawSpeed": 2.625, "serviceAttitude": 3.125, "websiteExperience": 2.875, "tzjPj": "", "zonghezhishu": 0}, {"platStatus": 1, "firstPin": "Y", "platEarnings": 9.63, "zonghezhishuRank": 0, "onlineDate": "2015-08-18", "salaryguard": 4.4706, "cityName": "广东|深圳", "platNamePin": "ydq", "platIconUrl": "http://www.wdzj.com/wdzj/images/plat/icon/2639.jpg", "registeredCapital": 10000, "gjlhhFlag": "0", "platName": "一点钱", "term": "6-12月标(1.5%)", "platId": 2639, "withdrawSpeed": 3.1176, "serviceAttitude": 4.2941, "websiteExperience": 4.3529, "tzjPj": "", "zonghezhishu": 0}, {"platStatus": 3, "firstPin": "J", "platEarnings": 16, "zonghezhishuRank": 0, "onlineDate": "2015-02-06", "cityName": "湖南|长沙", "platNamePin": "jhd3", "platIconUrl": "http://www.wdzj.com/wdzj/images/plat/icon/noicon.png", "registeredCapital": 3000, "gjlhhFlag": "0", "platName": "建辉贷", "term": "2月标(30%)、3月标(20%)", "platId": 1803, "tzjPj": "", "zonghezhishu": 0}, {"platStatus": 2, "firstPin": "Y", "platEarnings": 22.8, "zonghezhishuRank": 0, "onlineDate": "2015-03-16", "cityName": "湖南|长沙", "platNamePin": "yjzx", "platIconUrl": "http://www.wdzj.com/wdzj/images/plat/icon/1895.jpg", "registeredCapital": 1000, "gjlhhFlag": "0", "platName": "银嘉在线", "term": "2月标(100%)", "platId": 1895, "tzjPj": "", "zonghezhishu": 0}, {"platStatus": 2, "firstPin": "H", "platEarnings": 14.4, "zonghezhishuRank": 0, "onlineDate": "2014-11-19", "cityName": "重庆|江北", "platNamePin": "hxd4", "platIconUrl": "http://www.wdzj.com/wdzj/images/plat/icon/1714.jpg", "registeredCapital": 10000, "gjlhhFlag": "0", "platName": "惠信贷", "term": "4-6月标(51%)、2月标(49%)", "platId": 1714, "tzjPj": "", "zonghezhishu": 0}, {"platStatus": 2, "firstPin": "J", "platEarnings": 12, "zonghezhishuRank": 0, "salaryguard": 3.5333, "onlineDate": "2015-02-09", "cityName": "陕西|延安", "platNamePin": "jcd", "registeredCapital": 9981, "platIconUrl": "http://www.wdzj.com/wdzj/images/plat/icon/1644.jpg", "gjlhhFlag": "0", "platName": "吉成贷", "term": "3月标(50%)、1月标(50%)", "platId": 1644, "serviceAttitude": 3.1556, "withdrawSpeed": 2.7111, "websiteExperience": 3.0444, "tzjPj": "", "zonghezhishu": 0}, {"platStatus": 5, "firstPin": "K", "platEarnings": 0, "zonghezhishuRank": 0, "onlineDate": "2015-05-26", "cityName": "黑龙江|双鸭山", "platNamePin": "kled", "platIconUrl": "http://openplat.wdzj.com/upload/plats/2487/20150810164705s_.png", "registeredCapital": 500, "gjlhhFlag": "0", "platName": "快乐e贷", "term": "6-12月标(60.0%)、4-6月标(30.0%)", "platId": 2487, "tzjPj": "", "zonghezhishu": 0}, {"platStatus": 1, "firstPin": "H", "platEarnings": 8, "zonghezhishuRank": 0, "salaryguard": 4.6, "onlineDate": "2015-09-01", "androidUrl": "http://www.jhs360.com/userfiles/release/hsbank_2.1.1_fdjf_release_reinforce.apk", "cityName": "上海|闵行", "platNamePin": "hsjf", "registeredCapital": 10000, "platIconUrl": "http://www.wdzj.com/wdzj/images/example/2016/10/08/20161008165852s_.png", "gjlhhFlag": "0", "platName": "花生金服", "term": "6-12月标(20.0%)、4-6月标(20.0%)", "platId": 5361, "serviceAttitude": 4.0, "withdrawSpeed": 2.4, "websiteExperience": 4.2, "wechat": "http://openplat.wdzj.com/upload/plats/5361/20161020105003s_.jpg", "iosUrl": "https://itunes.apple.com/cn/app/hua-sheng-jin-fu/id1060369794?mt=8", "tzjPj": "", "zonghezhishu": 0}, {"platStatus": 2, "firstPin": "H", "platEarnings": 0, "zonghezhishuRank": 0, "onlineDate": "2015-10-12", "cityName": "江苏|宿迁", "platNamePin": "hhtz", "platIconUrl": "http://openplat.wdzj.com/upload/plats/3205/20151021162410s_.png", "registeredCapital": 1000, "gjlhhFlag": "0", "platName": "火狐投资", "term": "1月标(90.0%)、天标(10.0%)", "platId": 3205, "tzjPj": "", "zonghezhishu": 0}], "set": ""}