{"pageSize": 25, "currentPage": 27, "maxElements": 5594, "totalPage": 224, "liststep": 2, "listbegin": 26, "listend": 28, "offset": 0, "list": [{"platStatus": 5, "firstPin": "B", "platEarnings": 20.8, "zonghezhishuRank": 0, "salaryguard": 3.5, "onlineDate": "2015-03-28", "cityName": "山东|潍坊", "platNamePin": "bcct", "registeredCapital": 5000, "platIconUrl": "http://www.wdzj.com/wdzj/images/plat/icon/1766.jpg", "gjlhhFlag": "0", "platName": "百川创投", "term": "1月标(72%)、2月标(20%)", "platId": 1766, "serviceAttitude": 4.0, "withdrawSpeed": 3.75, "websiteExperience": 3.75, "tzjPj": "", "zonghezhishu": 0}, {"platStatus": 1, "firstPin": "G", "platEarnings": 11, "zonghezhishuRank": 0, "salaryguard": 4.0, "onlineDate": "2014-08-04", "androidUrl": "", "cityName": "广东|深圳", "platNamePin": "gft", "registeredCapital": 3000, "platIconUrl": "http://www.wdzj.com/wdzj/images/plat/icon/824.jpg", "gjlhhFlag": "0", "platName": "国富通", "platId": 824, "serviceAttitude": 3.5833, "withdrawSpeed": 2.75, "websiteExperience": 3.4167, "wechat": "http://openplat.wdzj.com/upload/plats/824/20160317095446s_.jpg", "iosUrl": "", "tzjPj": "", "zonghezhishu": 0}, {"platStatus": 2, "firstPin": "D", "platEarnings": 18, "zonghezhishuRank": 0, "salaryguard": 4.4211, "onlineDate": "2014-09-05", "cityName": "广东|深圳", "platNamePin": "ddlc", "registeredCapital": 1000, "platIconUrl": "http://www.wdzj.com/wdzj/images/plat/icon/839.jpg", "gjlhhFlag": "0", "platName": "点点理财", "term": "1月标(100%)", "platId": 839, "serviceAttitude": 3.8421, "withdrawSpeed": 2.8421, "websiteExperience": 3.7368, "tzjPj": "", "zonghezhishu": 0}, {"platStatus": 5, "firstPin": "Y", "platEarnings": 0, "zonghezhishuRank": 0, "salaryguard": 1.0, "onlineDate": "2015-07-20", "cityName": "福建|三明", "platNamePin": "yzd", "registeredCapital": 1500, "platIconUrl": "http://www.wdzj.com/wdzj/images/plat/icon/noicon.png", "gjlhhFlag": "0", "platName": "一站贷", "term": "2月标(35%)、1月标(35%)", "platId": 2342, "serviceAttitude": 1.0, "withdrawSpeed": 1.0, "websiteExperience": 1.0, "tzjPj": "", "zonghezhishu": 0}, {"platStatus": 2, "firstPin": "C", "platEarnings": 18, "zonghezhishuRank": 0, "salaryguard": 3.0, "onlineDate": "2014-12-25", "cityName": "河北|石家庄", "platNamePin": "cfd1", "registeredCapital": 5000, "platIconUrl": "http://openplat.wdzj.com/upload/plats/1232/20150127110826s_.png", "gjlhhFlag": "0", "platName": "创富贷", "platId": 1232, "serviceAttitude": 4.0, "withdrawSpeed": 4.0, "websiteExperience": 3.0, "tzjPj": "", "zonghezhishu": 0}, {"platStatus": 1, "firstPin": "L", "platEarnings": 14.31, "zonghezhishuRank": 0, "salaryguard": 4.0, "onlineDate": "2015-04-01", "androidUrl": "", "cityName": "福建|福州", "platNamePin": "ltcf6", "registeredCapital": 3000, "platIconUrl": "http://openplat.wdzj.com/upload/plats/2203/20170706165730s_.png", "gjlhhFlag": "0", "platName": "乐投创富", "term": "6-12月标(19.0%)", "platId": 2203, "serviceAttitude": 4.125, "withdrawSpeed": 3.25, "websiteExperience": 4.0, "wechat": "http://openplat.wdzj.com/upload/plats/2203/20170713174914s_.jpg", "iosUrl": "https://itunes.apple.com/cn/app/id1212182900", "tzjPj": "", "zonghezhishu": 0}, {"platStatus": 2, "firstPin": "H", "platEarnings": 13.8, "zonghezhishuRank": 0, "salaryguard": 4.3333, "onlineDate": "2015-09-15", "cityName": "广东|深圳", "platNamePin": "hxyb", "registeredCapital": 1000, "platIconUrl": "http://openplat.wdzj.com/upload/plats/3112/20151012135917s_.png", "gjlhhFlag": "0", "platName": "华夏银帮", "platId": 3112, "serviceAttitude": 4.6667, "withdrawSpeed": 5.0, "websiteExperience": 4.3333, "tzjPj": "", "zonghezhishu": 0}, {"platStatus": 1, "firstPin": "H", "platEarnings": 15, "zonghezhishuRank": 0, "onlineDate": "2014-04-08", "cityName": "广东|佛山", "platNamePin": "hdcf1", "platIconUrl": "http://www.wdzj.com/wdzj/images/plat/icon/550.jpg", "registeredCapital": 1000, "gjlhhFlag": "0", "platName": "亨多财富", "term": "1月标(95%)、天标(5%)", "platId": 550, "tzjPj": "", "zonghezhishu": 0}, {"platStatus": 3, "firstPin": "C", "platEarnings": 21.6, "zonghezhishuRank": 0, "salaryguard": 3.3333, "onlineDate": "2014-12-28", "cityName": "湖北|武汉", "platNamePin": "cxzt", "registeredCapital": 1000, "platIconUrl": "http://www.wdzj.com/wdzj/images/plat/icon/noicon.png", "gjlhhFlag": "0", "platName": "创新众投", "term": "1月标(63%)、2月标(35%)", "platId": 1770, "serviceAttitude": 2.1667, "withdrawSpeed": 1.6667, "websiteExperience": 2.0, "tzjPj": "", "zonghezhishu": 0}, {"platStatus": 1, "firstPin": "Q", "platEarnings": 12.57, "zonghezhishuRank": 0, "salaryguard": 4.1, "onlineDate": "2014-04-15", "androidUrl": "http://sj.qq.com/myapp/detail.htm?apkName=com.android.qqlc.financ", "cityName": "北京|石景山", "platNamePin": "qqxd", "registeredCapital": 5000, "platIconUrl": "http://openplat.wdzj.com/upload/plats/4506/20170714113307s_.png", "gjlhhFlag": "0", "platName": "亲亲小贷", "term": "6-12月标(30.1%)", "platId": 4506, "serviceAttitude": 4.5, "withdrawSpeed": 3.8, "websiteExperience": 4.4, "wechat": "http://openplat.wdzj.com/upload/plats/4506/20160621101639s_.jpg", "iosUrl": "https://itunes.apple.com/cn/app/qin-qin-li-cai/id994818613?mt=8", "tzjPj": "", "zonghezhishu": 0}, {"platStatus": 5, "firstPin": "Q", "platEarnings": 0, "zonghezhishuRank": 0, "onlineDate": "2015-06-08", "cityName": "江苏|南通", "platNamePin": "qhxd", "platIconUrl": "http://openplat.wdzj.com/upload/plats/2169/20150907160226s_.png", "registeredCapital": 3000, "gjlhhFlag": "0", "platName": "强宏信贷", "term": "1月标(50.0%)、2月标(30.0%)", "platId": 2169, "tzjPj": "", "zonghezhishu": 0}, {"platStatus": 1, "firstPin": "W", "platEarnings": 9, "zonghezhishuRank": 0, "salaryguard": 4.1667, "onlineDate": "2014-09-05", "cityName": "北京|朝阳", "platNamePin": "wtz", "registeredCapital": 2000, "platIconUrl": "http://www.wdzj.com/wdzj/images/plat/icon/2009.jpg", "gjlhhFlag": "0", "platName": "沃投资", "term": "1月标(75%)、2月标(15%)", "platId": 2009, "serviceAttitude": 4.0556, "withdrawSpeed": 3.7778, "websiteExperience": 3.7778, "tzjPj": "", "zonghezhishu": 0}, {"platStatus": 5, "firstPin": "T", "platEarnings": 20, "zonghezhishuRank": 0, "salaryguard": 3.0, "onlineDate": "2014-12-29", "cityName": "山东|潍坊", "platNamePin": "thcf", "registeredCapital": 600, "platIconUrl": "http://www.wdzj.com/wdzj/images/plat/icon/1663.jpg", "gjlhhFlag": "0", "platName": "天昊财富", "term": "1月标(100%)", "platId": 1663, "serviceAttitude": 2.5, "withdrawSpeed": 2.5, "websiteExperience": 2.0, "tzjPj": "", "zonghezhishu": 0}, {"platStatus": 5, "firstPin": "Z", "platEarnings": 0, "zonghezhishuRank": 0, "onlineDate": "2015-03-11", "cityName": "湖南|长沙", "platNamePin": "zjzx1", "platIconUrl": "http://openplat.wdzj.com/upload/plats/1506/20150311162520s_.png", "registeredCapital": 2000, "gjlhhFlag": "0", "platName": "中金在线", "term": "3月标(50%)、2月标(30%)", "platId": 1506, "tzjPj": "", "zonghezhishu": 0}, {"platStatus": 1, "firstPin": "W", "platEarnings": 9.83, "zonghezhishuRank": 0, "salaryguard": 4.0667, "onlineDate": "2015-01-11", "cityName": "上海|松江", "platNamePin": "wwd111", "registeredCapital": 3000, "platIconUrl": "http://www.wdzj.com/wdzj/images/plat/icon/1473.jpg", "gjlhhFlag": "0", "platName": "喔喔贷", "term": "6-12月标(46.7%)", "platId": 1473, "serviceAttitude": 4.0667, "withdrawSpeed": 4.4667, "websiteExperience": 4.3333, "tzjPj": "", "zonghezhishu": 0}, {"platStatus": 3, "firstPin": "Y", "platEarnings": 21.6, "zonghezhishuRank": 0, "salaryguard": 5.0, "onlineDate": "2015-01-12", "cityName": "湖北|武汉", "platNamePin": "yjrcf", "registeredCapital": 5000, "platIconUrl": "http://www.wdzj.com/wdzj/images/plat/icon/1424.jpg", "gjlhhFlag": "0", "platName": "一家人财富", "term": "4-6月标(50.0%)、1月标(27.0%)", "platId": 1424, "serviceAttitude": 5.0, "withdrawSpeed": 2.0, "websiteExperience": 5.0, "tzjPj": "", "zonghezhishu": 0}, {"platStatus": 1, "firstPin": "H", "platEarnings": 8.8, "zonghezhishuRank": 0, "salaryguard": 3.8723, "onlineDate": "2014-09-15", "androidUrl": "http://android.myapp.com/myapp/detail.htm?apkName=com.haolyy.haolyy", "cityName": "上海|杨浦", "platNamePin": "hlw", "registeredCapital": 10000, "platIconUrl": "http://openplat.wdzj.com/upload/plats/851/20170424124458s_.png", "gjlhhFlag": "0", "platName": "好利网", "term": "4-6月标(70.0%)、12-24月标(12.0%)", "platId": 851, "serviceAttitude": 3.7021, "withdrawSpeed": 3.3404, "websiteExperience": 3.6596, "wechat": "http://openplat.wdzj.com/upload/plats/851/20170418164441s_.jpg", "iosUrl": "https://itunes.apple.com/cn/app/hao-li-wang-li-cai-tou-zi/id1035193004?mt=8", "tzjPj": "", "zonghezhishu": 0}, {"platStatus": 1, "firstPin": "F", "platEarnings": 13, "zonghezhishuRank": 0, "salaryguard": 4.5, "onlineDate": "2014-08-08", "cityName": "浙江|杭州", "platNamePin": "fcd12", "registeredCapital": 3180, "platIconUrl": "http://www.wdzj.com/wdzj/images/plat/icon/1291.jpg", "gjlhhFlag": "0", "platName": "富春贷", "term": "1月标(100%)", "platId": 1291, "serviceAttitude": 4.3333, "withdrawSpeed": 3.1667, "websiteExperience": 4.1667, "tzjPj": "", "zonghezhishu": 0}, {"platStatus": 1, "firstPin": "Z", "platEarnings": 12.5, "zonghezhishuRank": 0, "salaryguard": 2.6667, "onlineDate": "2014-10-01", "cityName": "海南|海口", "platNamePin": "zd", "registeredCapital": 1000, "platIconUrl": "http://www.wdzj.com/wdzj/images/example/2016/05/13/20160513154100s_.jpg", "gjlhhFlag": "0", "platName": "众贷", "term": "1月标(50%)、2月标(30%)", "platId": 1284, "serviceAttitude": 3.0, "withdrawSpeed": 2.3333, "websiteExperience": 3.0, "tzjPj": "", "zonghezhishu": 0}, {"platStatus": 1, "firstPin": "T", "platEarnings": 0, "zonghezhishuRank": 0, "salaryguard": 3.5294, "onlineDate": "2014-11-11", "androidUrl": "http://sd.domobcdn.com/ugc/1149731.apk", "cityName": "贵州|贵阳", "platNamePin": "tsy", "registeredCapital": 5000, "platIconUrl": "http://www.wdzj.com/wdzj/images/plat/icon/1234.jpg", "gjlhhFlag": "0", "platName": "淘收益", "term": "3月标(60.0%)、6-12月标(30.0%)", "platId": 1234, "serviceAttitude": 4.0588, "withdrawSpeed": 3.0588, "websiteExperience": 3.9412, "wechat": "http://openplat.wdzj.com/upload/plats/1234/20170116164421s_.png", "iosUrl": "https://itunes.apple.com/cn/app/tao-shou-yi/id1073804475?mt=8", "tzjPj": "", "zonghezhishu": 0}, {"platStatus": 5, "firstPin": "L", "platEarnings": 17, "zonghezhishuRank": 0, "onlineDate": "2014-09-01", "cityName": "广东|深圳", "platNamePin": "lyyhx", "platIconUrl": "http://www.wdzj.com/wdzj/images/plat/icon/1217.jpg", "registeredCapital": 1000, "gjlhhFlag": "0", "platName": "荔园银河系", "platId": 1217, "tzjPj": "", "zonghezhishu": 0}, {"platStatus": 2, "firstPin": "L", "platEarnings": 13, "zonghezhishuRank": 0, "salaryguard": 4.25, "onlineDate": "2014-09-13", "cityName": "广东|深圳", "platNamePin": "ltr", "registeredCapital": 5000, "platIconUrl": "http://www.wdzj.com/wdzj/images/plat/icon/1154.jpg", "gjlhhFlag": "0", "platName": "利他人", "term": "2月标(60%)、1月标(40%)", "platId": 1154, "serviceAttitude": 4.5, "withdrawSpeed": 2.5, "websiteExperience": 4.5, "tzjPj": "", "zonghezhishu": 0}, {"platStatus": 1, "firstPin": "Y", "platEarnings": 10.76, "zonghezhishuRank": 0, "salaryguard": 5.0, "onlineDate": "2014-06-06", "cityName": "江西|抚州", "platNamePin": "yed", "registeredCapital": 1000, "platIconUrl": "http://www.wdzj.com/wdzj/images/plat/icon/637.jpg", "gjlhhFlag": "0", "platName": "易e贷", "term": "6-12月标(97.2%)", "platId": 637, "serviceAttitude": 4.0, "withdrawSpeed": 3.0, "websiteExperience": 4.0, "tzjPj": "", "zonghezhishu": 0}, {"platStatus": 2, "firstPin": "R", "platEarnings": 12, "zonghezhishuRank": 0, "onlineDate": "2015-06-05", "cityName": "湖北|武汉", "platNamePin": "rzd6", "platIconUrl": "http://www.wdzj.com/wdzj/images/plat/icon/2078.jpg", "registeredCapital": 1000, "gjlhhFlag": "0", "platName": "融资贷", "platId": 2078, "tzjPj": "", "zonghezhishu": 0}, {"platStatus": 1, "firstPin": "Q", "platEarnings": 13, "zonghezhishuRank": 0, "salaryguard": 4.6591, "onlineDate": "2015-05-08", "androidUrl": "http://zhushou.360.cn/detail/index/soft_id/3572446?recrefer=SE_D_%E5%89%8D%E6%B5%B7%E5%B9%BF%E6%B7%B", "cityName": "广东|深圳", "platNamePin": "qhgsf", "registeredCapital": 5000, "platIconUrl": "http://openplat.wdzj.com/upload/plats/1989/20160830142226s_.gif", "gjlhhFlag": "0", "platName": "前海广深发", "term": "24月以上标(25.0%)、6-12月标(25.0%)", "platId": 1989, "serviceAttitude": 4.3636, "withdrawSpeed": 3.6364, "websiteExperience": 4.2045, "wechat": "http://www.wdzj.com/wdzj/images/plats/2017/03/07/20170307162629s_.jpg", "iosUrl": "https://itunes.apple.com/cn/app/guang-shen-fa/id1146113532?mt=8", "tzjPj": "", "zonghezhishu": 0}], "set": ""}