{"pageSize": 25, "currentPage": 37, "maxElements": 5594, "totalPage": 224, "liststep": 2, "listbegin": 36, "listend": 38, "offset": 0, "list": [{"platStatus": 2, "firstPin": "B", "platEarnings": 8, "zonghezhishuRank": 0, "onlineDate": "2015-04-18", "cityName": "宁夏|银川", "platNamePin": "blw", "platIconUrl": "http://www.wdzj.com/wdzj/images/plat/icon/1886.jpg", "registeredCapital": 3000, "gjlhhFlag": "0", "platName": "本利网", "term": "2月标(30%)、1月标(30%)", "platId": 1886, "tzjPj": "", "zonghezhishu": 0}, {"platStatus": 2, "firstPin": "Z", "platEarnings": 15, "zonghezhishuRank": 0, "onlineDate": "2015-02-28", "cityName": "上海|浦东", "platNamePin": "zwcf", "platIconUrl": "http://openplat.wdzj.com/upload/plats/1578/20150310143906s_.jpg", "registeredCapital": 10000, "gjlhhFlag": "0", "platName": "中吴财富", "term": "2月标(40%)、1月标(30%)", "platId": 1578, "tzjPj": "", "zonghezhishu": 0}, {"platStatus": 2, "firstPin": "Y", "platEarnings": 15.6, "zonghezhishuRank": 0, "onlineDate": "2014-11-19", "cityName": "广东|深圳", "platNamePin": "yyb1", "platIconUrl": "http://www.wdzj.com/wdzj/images/plat/icon/1311.jpg", "registeredCapital": 7000, "gjlhhFlag": "0", "platName": "沄银宝", "term": "1月标(50%)、天标(50%)", "platId": 1311, "tzjPj": "", "zonghezhishu": 0}, {"platStatus": 2, "firstPin": "X", "platEarnings": 18, "zonghezhishuRank": 0, "salaryguard": 4.0, "onlineDate": "2015-05-18", "cityName": "上海|杨浦", "platNamePin": "xbzc", "registeredCapital": 2000, "platIconUrl": "http://www.wdzj.com/wdzj/images/plat/icon/noicon.png", "gjlhhFlag": "0", "platName": "巽邦资产", "term": "1月标(70%)、2月标(30%)", "platId": 2021, "serviceAttitude": 4.0, "withdrawSpeed": 4.0, "websiteExperience": 4.0, "tzjPj": "", "zonghezhishu": 0}, {"platStatus": 8, "firstPin": "C", "platEarnings": 15, "zonghezhishuRank": 0, "onlineDate": "2015-02-13", "cityName": "海南|海口", "platNamePin": "cyd3", "platIconUrl": "http://www.wdzj.com/wdzj/images/plat/icon/2916.jpg", "registeredCapital": 1000, "gjlhhFlag": "0", "platName": "创一贷", "term": "4-6月标(38.0%)、天标(22.0%)", "platId": 2916, "tzjPj": "", "zonghezhishu": 0}, {"platStatus": 2, "firstPin": "W", "platEarnings": 18, "zonghezhishuRank": 0, "onlineDate": "2014-06-24", "salaryguard": 1.0, "cityName": "福建|龙岩", "platNamePin": "wyd4", "platIconUrl": "http://www.wdzj.com/wdzj/images/plat/icon/1765.jpg", "registeredCapital": 2000, "gjlhhFlag": "0", "platName": "稳盈贷", "term": "1月标(70%)、2月标(30%)", "platId": 1765, "withdrawSpeed": 1.0, "serviceAttitude": 1.0, "websiteExperience": 1.0, "tzjPj": "", "zonghezhishu": 0}, {"platStatus": 2, "firstPin": "Q", "platEarnings": 18, "zonghezhishuRank": 0, "onlineDate": "2015-01-01", "salaryguard": 3.3636, "cityName": "北京|朝阳", "platNamePin": "qht", "platIconUrl": "http://www.wdzj.com/wdzj/images/plat/icon/1571.jpg", "registeredCapital": 1200, "gjlhhFlag": "0", "platName": "千和投", "term": "天标(60%)、1月标(30%)", "platId": 1571, "withdrawSpeed": 1.8182, "serviceAttitude": 3.0, "websiteExperience": 2.8182, "tzjPj": "", "zonghezhishu": 0}, {"platStatus": 1, "firstPin": "H", "platEarnings": 13, "zonghezhishuRank": 0, "onlineDate": "2015-07-18", "salaryguard": 4.5231, "cityName": "安徽|铜陵", "platNamePin": "hjm", "platIconUrl": "http://www.wdzj.com/wdzj/images/plat/icon/2552.jpg", "registeredCapital": 3000, "gjlhhFlag": "0", "platName": "徽金猫", "term": "1月标(40.0%)、4-6月标(20.0%)", "platId": 2552, "withdrawSpeed": 4.4462, "serviceAttitude": 4.4769, "websiteExperience": 4.4308, "tzjPj": "", "zonghezhishu": 0}, {"platStatus": 1, "firstPin": "M", "platEarnings": 19.2, "zonghezhishuRank": 0, "onlineDate": "2014-04-01", "salaryguard": 1.0, "cityName": "浙江|丽水", "platNamePin": "mrw", "platIconUrl": "http://www.wdzj.com/wdzj/images/plat/icon/1996.jpg", "registeredCapital": 1000, "gjlhhFlag": "0", "platName": "米融网", "term": "1月标(90%)、2月标(10%)", "platId": 1996, "withdrawSpeed": 1.0, "serviceAttitude": 1.0, "websiteExperience": 1.0, "tzjPj": "", "zonghezhishu": 0}, {"platStatus": 3, "firstPin": "D", "platEarnings": 21.6, "zonghezhishuRank": 0, "onlineDate": "2014-11-03", "salaryguard": 1.0, "cityName": "广东|深圳", "platNamePin": "dld1", "platIconUrl": "http://www.wdzj.com/wdzj/images/plat/icon/1869.jpg", "registeredCapital": 5000, "gjlhhFlag": "0", "platName": "德利贷", "term": "1月标(100%)", "platId": 1869, "withdrawSpeed": 1.0, "serviceAttitude": 1.0, "websiteExperience": 1.0, "tzjPj": "", "zonghezhishu": 0}, {"platStatus": 1, "firstPin": "H", "platEarnings": 11, "zonghezhishuRank": 0, "onlineDate": "2015-10-27", "salaryguard": 2.4, "androidUrl": "http://sdapp.heimazaixian.com/download_hmd_app/down.php", "cityName": "北京|东城", "platNamePin": "hmdzd", "platIconUrl": "http://openplat.wdzj.com/upload/plats/4570/20160708123629s_.jpg", "registeredCapital": 10000, "gjlhhFlag": "0", "platName": "黑马贷", "term": "1月标(74.0%)、3月标(19.0%)", "platId": 4570, "withdrawSpeed": 2.2, "serviceAttitude": 3.0, "websiteExperience": 2.8, "wechat": "http://openplat.wdzj.com/upload/plats/4570/20160708152853s_.jpg", "iosUrl": "https://itunes.apple.com/cn/app/hei-ma-dai/id1089806591?mt=8", "tzjPj": "", "zonghezhishu": 0}, {"platStatus": 2, "firstPin": "Z", "platEarnings": 11, "zonghezhishuRank": 0, "onlineDate": "2014-03-09", "salaryguard": 3.0, "cityName": "湖北|武汉", "platNamePin": "zmedw", "platIconUrl": "http://www.wdzj.com/wdzj/images/plat/icon/2390.jpg", "registeredCapital": 2000, "gjlhhFlag": "0", "platName": "芝麻e贷", "term": "6-12月标(35.0%)、4-6月标(27.0%)", "platId": 2390, "withdrawSpeed": 3.0, "serviceAttitude": 4.0, "websiteExperience": 4.0, "tzjPj": "", "zonghezhishu": 0}, {"platStatus": 2, "firstPin": "H", "platEarnings": 0, "zonghezhishuRank": 0, "onlineDate": "2015-09-01", "cityName": "北京|东城", "platNamePin": "htyb", "platIconUrl": "http://openplat.wdzj.com/upload/plats/3211/20151022160746s_.jpg", "registeredCapital": 10000, "gjlhhFlag": "0", "platName": "华泰100", "term": "1月标(75.0%)、4-6月标(25.0%)", "platId": 3211, "tzjPj": "", "zonghezhishu": 0}, {"platStatus": 5, "firstPin": "Y", "platEarnings": 14.4, "zonghezhishuRank": 0, "onlineDate": "2015-10-19", "salaryguard": 5.0, "cityName": "湖南|长沙", "platNamePin": "ycd8", "platIconUrl": "http://openplat.wdzj.com/upload/plats/3215/20151109153851s_.png", "registeredCapital": 1000, "gjlhhFlag": "0", "platName": "悦车贷", "term": "1月标(90.0%)、天标(10.0%)", "platId": 3215, "withdrawSpeed": 5.0, "serviceAttitude": 4.6667, "websiteExperience": 4.6667, "tzjPj": "", "zonghezhishu": 0}, {"platStatus": 1, "firstPin": "J", "platEarnings": 12, "zonghezhishuRank": 0, "salaryguard": 3.5714, "onlineDate": "2014-12-18", "cityName": "上海|浦东", "platNamePin": "jljr", "registeredCapital": 10000, "platIconUrl": "http://www.wdzj.com/wdzj/images/plat/icon/1873.jpg", "gjlhhFlag": "0", "platName": "巨涟金融", "term": "1月标(30.0%)、天标(30.0%)", "platId": 1873, "serviceAttitude": 3.1429, "withdrawSpeed": 2.2857, "websiteExperience": 3.0, "tzjPj": "", "zonghezhishu": 0}, {"platStatus": 2, "firstPin": "Y", "platEarnings": 15, "zonghezhishuRank": 0, "salaryguard": 3.7895, "onlineDate": "2015-02-09", "cityName": "湖南|长沙", "platNamePin": "ydjr1", "registeredCapital": 1000, "platIconUrl": "http://www.wdzj.com/wdzj/images/plat/icon/noicon.png", "gjlhhFlag": "0", "platName": "银达金融", "term": "1月标(70%)、2月标(30%)", "platId": 1615, "serviceAttitude": 3.3684, "withdrawSpeed": 2.9474, "websiteExperience": 3.2632, "tzjPj": "", "zonghezhishu": 0}, {"platStatus": 2, "firstPin": "Q", "platEarnings": 15, "zonghezhishuRank": 0, "salaryguard": 4.5, "onlineDate": "2015-01-10", "cityName": "陕西|西安", "platNamePin": "qzx", "registeredCapital": 2000, "platIconUrl": "http://www.wdzj.com/wdzj/images/plat/icon/1651.jpg", "gjlhhFlag": "0", "platName": "钱在线", "term": "1月标(50%)、4-6月标(25%)", "platId": 1651, "serviceAttitude": 4.5, "withdrawSpeed": 2.5, "websiteExperience": 4.5, "tzjPj": "", "zonghezhishu": 0}, {"platStatus": 2, "firstPin": "Q", "platEarnings": 14, "zonghezhishuRank": 0, "onlineDate": "2014-11-08", "cityName": "四川|成都", "platNamePin": "qkd1", "platIconUrl": "http://openplat.wdzj.com/upload/plats/1452/20150130145706s_.png", "registeredCapital": 1000, "gjlhhFlag": "0", "platName": "钱口贷", "term": "1月标(40%)、2月标(35%)", "platId": 1452, "tzjPj": "", "zonghezhishu": 0}, {"platStatus": 2, "firstPin": "Y", "platEarnings": 15.6, "zonghezhishuRank": 0, "salaryguard": 4.0, "onlineDate": "2014-07-12", "cityName": "江苏|无锡", "platNamePin": "yyd3", "registeredCapital": 500, "platIconUrl": "http://www.wdzj.com/wdzj/images/plat/icon/1365.jpg", "gjlhhFlag": "0", "platName": "易友贷", "term": "1月标(50%)、天标(30%)", "platId": 1365, "serviceAttitude": 3.0, "withdrawSpeed": 2.5, "websiteExperience": 3.0, "tzjPj": "", "zonghezhishu": 0}, {"platStatus": 3, "firstPin": "Z", "platEarnings": 16.8, "zonghezhishuRank": 0, "salaryguard": 3.5, "onlineDate": "2014-08-05", "cityName": "福建|泉州", "platNamePin": "zdzx", "registeredCapital": 20000, "platIconUrl": "http://www.wdzj.com/wdzj/images/plat/icon/1259.jpg", "gjlhhFlag": "0", "platName": "中鼎在线", "term": "2月标(80%)、1月标(20%)", "platId": 1259, "serviceAttitude": 3.0, "withdrawSpeed": 2.25, "websiteExperience": 2.75, "tzjPj": "", "zonghezhishu": 0}, {"platStatus": 2, "firstPin": "G", "platEarnings": 18, "zonghezhishuRank": 0, "onlineDate": "2015-03-13", "cityName": "广西|梧州", "platNamePin": "gfcf9", "platIconUrl": "http://www.wdzj.com/wdzj/images/plat/icon/2252.jpg", "registeredCapital": 1000, "gjlhhFlag": "0", "platName": "广发财富", "term": "1月标(80%)、2月标(15%)", "platId": 2252, "tzjPj": "", "zonghezhishu": 0}, {"platStatus": 5, "firstPin": "S", "platEarnings": 18, "zonghezhishuRank": 0, "onlineDate": "2015-07-01", "cityName": "山东|聊城", "platNamePin": "sklcf", "platIconUrl": "http://www.wdzj.com/wdzj/images/plat/icon/2231.jpg", "registeredCapital": 2000, "gjlhhFlag": "0", "platName": "盛凯禄财富", "term": "天标(40%)、2月标(30%)", "platId": 2231, "tzjPj": "", "zonghezhishu": 0}, {"platStatus": 2, "firstPin": "R", "platEarnings": 10.5, "zonghezhishuRank": 0, "salaryguard": 5.0, "onlineDate": "2015-07-13", "cityName": "上海|浦东", "platNamePin": "rwx", "registeredCapital": 10000, "platIconUrl": "http://openplat.wdzj.com/upload/plats/4035/20160216110617s_.jpg", "gjlhhFlag": "0", "platName": "仁我行", "term": "3月标(20.0%)、2月标(20.0%)", "platId": 4035, "serviceAttitude": 5.0, "withdrawSpeed": 3.0, "websiteExperience": 5.0, "tzjPj": "", "zonghezhishu": 0}, {"platStatus": 1, "firstPin": "L", "platEarnings": 13.7, "zonghezhishuRank": 0, "salaryguard": 4.2222, "onlineDate": "2015-05-28", "cityName": "内蒙古|包头", "platNamePin": "lxd5", "registeredCapital": 5000, "platIconUrl": "http://www.wdzj.com/wdzj/images/plat/icon/2067.jpg", "gjlhhFlag": "0", "platName": "联鑫贷", "term": "1月标(40%)、3月标(30%)", "platId": 2067, "serviceAttitude": 4.1111, "withdrawSpeed": 3.5556, "websiteExperience": 3.7778, "tzjPj": "", "zonghezhishu": 0}, {"platStatus": 2, "firstPin": "D", "platEarnings": 20, "zonghezhishuRank": 0, "onlineDate": "2015-05-10", "cityName": "山东|青岛", "platNamePin": "dtcf", "platIconUrl": "http://www.wdzj.com/wdzj/images/plat/icon/1985.jpg", "registeredCapital": 2000, "gjlhhFlag": "0", "platName": "帝天财富", "term": "1月标(55%)、2月标(45%)", "platId": 1985, "tzjPj": "", "zonghezhishu": 0}], "set": ""}