{"list": {"data": [{"title": "贫民窟的百万富翁", "link": "https://pan.baidu.com/share/link?shareid=2689611404&uk=740383300", "des": "文件数: 1,分享时间: 2015-12-02T21:29:22, 文件大小: 1k", "blink": "https://pan.baidu.com/share/link?shareid=2689611404&uk=740383300", "host": "pan.baidu.com", "more": null}, {"title": "贫民窟的百万富翁", "link": "https://pan.baidu.com/share/link?shareid=1643908377&uk=481079506", "des": "文件数: 1,分享时间: 2017-03-03T19:03:44, 文件大小: 1k", "blink": "https://pan.baidu.com/share/link?shareid=1643908377&uk=481079506", "host": "pan.baidu.com", "more": null}, {"title": "《贫民窟的百万富翁》", "link": "https://pan.baidu.com/share/link?shareid=489865280&uk=1280729612", "des": "文件数: 1,分享时间: 2016-02-07T17:59:30, 文件大小: 1k", "blink": "https://pan.baidu.com/share/link?shareid=489865280&uk=1280729612", "host": "pan.baidu.com", "more": null}, {"title": "贫民窟的百万富翁", "link": "https://pan.baidu.com/share/link?shareid=992759439&uk=805577464", "des": "文件数: 1,分享时间: 2013-12-15T21:02:46, 文件大小: 1k", "blink": "https://pan.baidu.com/share/link?shareid=992759439&uk=805577464", "host": "pan.baidu.com", "more": null}, {"title": "贫民窟的百万富翁", "link": "https://pan.baidu.com/share/link?shareid=420263084&uk=4013056225", "des": "文件数: 1,分享时间: 2017-02-17T10:42:36, 文件大小: 1k", "blink": "https://pan.baidu.com/share/link?shareid=420263084&uk=4013056225", "host": "pan.baidu.com", "more": null}, {"title": "贫民窟的百万富翁", "link": "https://pan.baidu.com/share/link?shareid=1717819797&uk=1931962571", "des": "文件数: 1,分享时间: 2015-04-24T01:56:31, 文件大小: 1k", "blink": "https://pan.baidu.com/share/link?shareid=1717819797&uk=1931962571", "host": "pan.baidu.com", "more": null}, {"title": "贫民窟的百万富翁", "link": "https://pan.baidu.com/share/link?shareid=938020365&uk=1902651040", "des": "文件数: 1,分享时间: 2016-03-20T13:23:45, 文件大小: 1k", "blink": "https://pan.baidu.com/share/link?shareid=938020365&uk=1902651040", "host": "pan.baidu.com", "more": null}, {"title": "贫民窟的百万富翁", "link": "https://pan.baidu.com/share/link?shareid=935858474&uk=1902651040", "des": "文件数: 1,分享时间: 2016-03-20T13:23:23, 文件大小: 1k", "blink": "https://pan.baidu.com/share/link?shareid=935858474&uk=1902651040", "host": "pan.baidu.com", "more": null}, {"title": "贫民窟的百万富翁", "link": "https://pan.baidu.com/share/link?shareid=1956398394&uk=1814337724", "des": "文件数: 1,分享时间: 2016-04-03T02:20:50, 文件大小: 1k", "blink": "https://pan.baidu.com/share/link?shareid=1956398394&uk=1814337724", "host": "pan.baidu.com", "more": null}, {"title": "贫民窟的百万富翁", "link": "https://pan.baidu.com/share/link?shareid=3221446224&uk=2258135478", "des": "文件数: 1,分享时间: 2017-01-23T18:30:00, 文件大小: 1k", "blink": "https://pan.baidu.com/share/link?shareid=3221446224&uk=2258135478", "host": "pan.baidu.com", "more": null}], "count": 467, "q": "贫民窟的百万富翁 ", "p": "1", "runtime": 0.5, "from": "baidu"}, "listcount": 10, "description": "贫民窟的百万富翁 相关信息"}