{"list": {"data": [{"title": "大卫·戈尔的一生", "link": "https://pan.baidu.com/share/link?shareid=451785582&uk=1515339266", "des": "文件数: 1,分享时间: 2015-07-09T11:43:00, 文件大小: 1k", "blink": "https://pan.baidu.com/share/link?shareid=451785582&uk=1515339266", "host": "pan.baidu.com", "more": null}, {"title": "大卫·戈尔的一生", "link": "https://pan.baidu.com/share/link?shareid=56563585&uk=3764406524", "des": "文件数: 1,分享时间: 2016-06-13T09:19:26, 文件大小: 1k", "blink": "https://pan.baidu.com/share/link?shareid=56563585&uk=3764406524", "host": "pan.baidu.com", "more": null}, {"title": "大卫戈尔的一生", "link": "https://pan.baidu.com/share/link?shareid=4074518975&uk=2258135478", "des": "文件数: 1,分享时间: 2017-01-26T20:41:49, 文件大小: 1k", "blink": "https://pan.baidu.com/share/link?shareid=4074518975&uk=2258135478", "host": "pan.baidu.com", "more": null}, {"title": "大卫·戈尔的一生", "link": "https://pan.baidu.com/share/link?shareid=2524898643&uk=3764406524", "des": "文件数: 1,分享时间: 2016-07-24T16:49:33, 文件大小: 1k", "blink": "https://pan.baidu.com/share/link?shareid=2524898643&uk=3764406524", "host": "pan.baidu.com", "more": null}, {"title": "大卫·戈尔的一生", "link": "https://pan.baidu.com/share/link?shareid=2200973645&uk=2701181026", "des": "文件数: 1,分享时间: 2016-06-16T09:01:41, 文件大小: 1k", "blink": "https://pan.baidu.com/share/link?shareid=2200973645&uk=2701181026", "host": "pan.baidu.com", "more": null}, {"title": "大卫·戈尔的一生", "link": "https://pan.baidu.com/share/link?shareid=1254679189&uk=3993130536", "des": "文件数: 1,分享时间: 2015-10-10T12:56:38, 文件大小: 1k", "blink": "https://pan.baidu.com/share/link?shareid=1254679189&uk=3993130536", "host": "pan.baidu.com", "more": null}, {"title": "大卫戈尔的一生", "link": "https://pan.baidu.com/share/link?shareid=1711758941&uk=155552758", "des": "文件数: 1,分享时间: 2017-04-23T13:54:10, 文件大小: 1k", "blink": "https://pan.baidu.com/share/link?shareid=1711758941&uk=155552758", "host": "pan.baidu.com", "more": null}, {"title": "大卫.戈尔的一生", "link": "https://pan.baidu.com/share/link?shareid=4261177058&uk=187713544", "des": "文件数: 1,分享时间: 2016-11-03T18:52:24, 文件大小: 1k", "blink": "https://pan.baidu.com/share/link?shareid=4261177058&uk=187713544", "host": "pan.baidu.com", "more": null}, {"title": "大卫·戈尔的一生", "link": "https://pan.baidu.com/share/link?shareid=3591138793&uk=3728659900", "des": "文件数: 1,分享时间: 2015-12-29T20:14:20, 文件大小: 1k", "blink": "https://pan.baidu.com/share/link?shareid=3591138793&uk=3728659900", "host": "pan.baidu.com", "more": null}, {"title": "大卫戈尔的一生", "link": "https://pan.baidu.com/share/link?shareid=4180615820&uk=4127742961", "des": "文件数: 1,分享时间: 2015-07-15T09:18:35, 文件大小: 1k", "blink": "https://pan.baidu.com/share/link?shareid=4180615820&uk=4127742961", "host": "pan.baidu.com", "more": null}], "count": 2000, "q": "大卫·戈尔的一生 ", "p": "1", "runtime": 0.5, "from": "baidu"}, "listcount": 10, "description": "大卫·戈尔的一生 相关信息"}