{"list": {"data": [{"title": "蝴蝶", "link": "https://pan.baidu.com/share/link?shareid=1849672524&uk=2200117301", "des": "文件数: 1,分享时间: 2014-12-26T18:51:27, 文件大小: 1k", "blink": "https://pan.baidu.com/share/link?shareid=1849672524&uk=2200117301", "host": "pan.baidu.com", "more": null}, {"title": "蝴蝶", "link": "https://pan.baidu.com/share/link?shareid=3888540241&uk=3819391060", "des": "文件数: 1,分享时间: 2016-12-09T22:09:17, 文件大小: 1k", "blink": "https://pan.baidu.com/share/link?shareid=3888540241&uk=3819391060", "host": "pan.baidu.com", "more": null}, {"title": "蝴蝶", "link": "https://pan.baidu.com/share/link?shareid=114199422&uk=4051721367", "des": "文件数: 1,分享时间: 2016-01-24T18:53:43, 文件大小: 1k", "blink": "https://pan.baidu.com/share/link?shareid=114199422&uk=4051721367", "host": "pan.baidu.com", "more": null}, {"title": "蝴蝶", "link": "https://pan.baidu.com/share/link?shareid=386756287&uk=3993130536", "des": "文件数: 1,分享时间: 2015-10-09T22:36:09, 文件大小: 1k", "blink": "https://pan.baidu.com/share/link?shareid=386756287&uk=3993130536", "host": "pan.baidu.com", "more": null}, {"title": "蝴蝶", "link": "https://pan.baidu.com/share/link?shareid=943712282&uk=675111558", "des": "文件数: 1,分享时间: 2016-08-29T23:04:38, 文件大小: 1k", "blink": "https://pan.baidu.com/share/link?shareid=943712282&uk=675111558", "host": "pan.baidu.com", "more": null}, {"title": "蝴蝶", "link": "https://pan.baidu.com/share/link?shareid=1093344399&uk=3542931456", "des": "文件数: 1,分享时间: 2015-02-12T22:00:42, 文件大小: 1k", "blink": "https://pan.baidu.com/share/link?shareid=1093344399&uk=3542931456", "host": "pan.baidu.com", "more": null}, {"title": "蝴蝶", "link": "https://pan.baidu.com/share/link?shareid=1250591644&uk=1459987268", "des": "文件数: 1,分享时间: 2016-06-30T09:14:27, 文件大小: 1k", "blink": "https://pan.baidu.com/share/link?shareid=1250591644&uk=1459987268", "host": "pan.baidu.com", "more": null}, {"title": "蝴蝶", "link": "https://pan.baidu.com/share/link?shareid=16763128&uk=3849557806", "des": "文件数: 1,分享时间: 2015-09-06T14:14:01, 文件大小: 1k", "blink": "https://pan.baidu.com/share/link?shareid=16763128&uk=3849557806", "host": "pan.baidu.com", "more": null}, {"title": "蝴蝶", "link": "https://pan.baidu.com/share/link?shareid=2723737423&uk=3157223751", "des": "文件数: 1,分享时间: 2013-11-13T18:22:26, 文件大小: 1k", "blink": "https://pan.baidu.com/share/link?shareid=2723737423&uk=3157223751", "host": "pan.baidu.com", "more": null}, {"title": "蝴蝶", "link": "https://pan.baidu.com/share/link?shareid=4217470321&uk=2938990077", "des": "文件数: 1,分享时间: 2017-03-28T02:09:30, 文件大小: 1k", "blink": "https://pan.baidu.com/share/link?shareid=4217470321&uk=2938990077", "host": "pan.baidu.com", "more": null}], "count": 2000, "q": "蝴蝶 ", "p": "1", "runtime": 0.5, "from": "baidu"}, "listcount": 10, "description": "蝴蝶 相关信息"}